angent/__init__.py
angent/py.typed
angent/types.py
angent-0.1.0.dist-info/METADATA
angent-0.1.0.dist-info/WHEEL
angent-0.1.0.dist-info/RECORD
